finelpy/.DS_Store
finelpy/__init__.py
finelpy/analysis/__init__.py
finelpy/analysis/analysis.py
finelpy/binding.cpp
finelpy/bindings/analysis_binding.cpp
finelpy/bindings/element_binding.cpp
finelpy/bindings/geometry_binding.cpp
finelpy/bindings/material_binding.cpp
finelpy/bindings/matrix_binding.cpp
finelpy/bindings/mesh_binding.cpp
finelpy/bindings/solver_binding.cpp
finelpy/core.cp312-win_amd64.pyd
finelpy/cpp/analysis/analysis.cpp
finelpy/cpp/compatibility.cpp
finelpy/cpp/element_geometry/line_elements.cpp
finelpy/cpp/element_geometry/quad.cpp
finelpy/cpp/element_geometry/tri.cpp
finelpy/cpp/element_physics/element_physics.cpp
finelpy/cpp/element_physics/plane.cpp
finelpy/cpp/elements/elements.cpp
finelpy/cpp/elements/integration.cpp
finelpy/cpp/elements/shape_funcs.cpp
finelpy/cpp/geometry/geometry.cpp
finelpy/cpp/material/elasticity.cpp
finelpy/cpp/material/material.cpp
finelpy/cpp/matrix/matrix.cpp
finelpy/cpp/matrix/petsc_funcs.cpp
finelpy/cpp/matrix/solvers.cpp
finelpy/cpp/mesh/mesh_and_mesher.cpp
finelpy/cpp/mesh/mesher_1d.cpp
finelpy/cpp/mesh/mesher_2d.cpp
finelpy/cpp/result/plot.cpp
finelpy/cpp/result/result.cpp
finelpy/cpp/solver/solver.cpp
finelpy/elements/__init__.py
finelpy/elements/elements.py
finelpy/elements/line_elements.py
finelpy/geometry/__init__.py
finelpy/geometry/geometry.py
finelpy/material/__init__.py
finelpy/material/material.py
finelpy/mesh/__init__.py
finelpy/mesh/mesh.py
finelpy/results/__init__.py
finelpy/results/results.py
finelpy/utils.py
finelpy-0.1.1.dist-info/METADATA
finelpy-0.1.1.dist-info/WHEEL
finelpy-0.1.1.dist-info/licenses/LICENSE
finelpy-0.1.1.dist-info/RECORD
