Metadata-Version: 2.4
Name: finelpy
Version: 0.1.1
Summary: Finite Element module
Author-Email: Heitor Lopes <hnlopes@unicamp.br>
License-File: LICENSE
Classifier: Programming Language :: Python :: 3
Classifier: Programming Language :: C++
Classifier: Operating System :: OS Independent
Classifier: License :: OSI Approved :: GNU General Public License v3 (GPLv3)
Requires-Python: >=3.8
Requires-Dist: numpy
Requires-Dist: scipy
Requires-Dist: matplotlib
